{"name": "manga", "isRoot": "yes", "children": [{"isMedia": "yes", "name": "manga", "children": [{"isGenre": "yes", "name": "action", "children": [{"isTheme": "yes", "name": "historical", "children": [{"isMovie": "yes", "name": "Devil Kings Basara"}, {"isMovie": "yes", "name": "Yahiko no Sakabato"}, {"isMovie": "yes", "name": "Burai"}, {"isMovie": "yes", "name": "Mutsu Enmei-ry\u016b Gaiden: Shura no Toki"}, {"isMovie": "yes", "name": "Dragon Sister!"}, {"isMovie": "yes", "name": "Ry\u016br\u014dden: Ch\u016bgen Ry\u014dran-hen"}, {"isMovie": "yes", "name": "Sanctuary - The Bakur\u014d Ishin"}, {"isMovie": "yes", "name": "Kingdom"}, {"isMovie": "yes", "name": "Tale of the Crescent Moon Dragon"}, {"isMovie": "yes", "name": "King's Moon: The Life of Akechi Mitsuhide"}, {"isMovie": "yes", "name": "Assassin's Creed 4: Black Flag -Kakusei-"}, {"isMovie": "yes", "name": "Baltzar Militarismus"}, {"isMovie": "yes", "name": "Kaze Hikaru"}, {"isMovie": "yes", "name": "Dororo"}, {"isMovie": "yes", "name": "Legend of Kamui"}, {"isMovie": "yes", "name": "Apocalypse Meow"}, {"isMovie": "yes", "name": "Basilisk"}, {"isMovie": "yes", "name": "Yagyu Ninja Scrolls"}, {"isMovie": "yes", "name": "Onimusha: Night Of Genesis"}, {"isMovie": "yes", "name": "Chrono Crusade"}, {"isMovie": "yes", "name": "Steamboy"}, {"isMovie": "yes", "name": "Daisan no Teikoku"}, {"isMovie": "yes", "name": "Hellsing: The Dawn"}, {"isMovie": "yes", "name": "Shigurui"}, {"isMovie": "yes", "name": "Knights"}, {"isMovie": "yes", "name": "Kacchu No Senshi Gamu"}, {"isMovie": "yes", "name": "Gorgeous Carat: L'Esperanza"}, {"isMovie": "yes", "name": "Yoakemono"}, {"isMovie": "yes", "name": "Kuro no Shishi"}, {"isMovie": "yes", "name": "Yu-Gi-Oh! Millennium World"}, {"isMovie": "yes", "name": "Red - Living on the Edge"}]}]}]}]}