{"ratings": [{"ratings": "9.2493", "anime": {"name": "Berserk"}}, {"ratings": "8.6644", "anime": {"name": "Betrayal Knows My Name"}}, {"ratings": "8.179", "anime": {"name": "Chrono Crusade"}}, {"ratings": "8.146", "anime": {"name": "Blue Exorcist"}}, {"ratings": "8.0549", "anime": {"name": "Kamisama Kiss"}}, {"ratings": "7.9932", "anime": {"name": "From Far Away"}}, {"ratings": "7.6934", "anime": {"name": "Tetragrammaton Labyrinth"}}, {"ratings": "7.6764", "anime": {"name": "3x3 Eyes"}}, {"ratings": "7.4795", "anime": {"name": "Tales of Destiny"}}, {"ratings": "7.2648", "anime": {"name": "Black Bird"}}, {"ratings": "6.8122", "anime": {"name": "Demon Ororon"}}, {"ratings": "6.648", "anime": {"name": "Baku"}}, {"ratings": "6.5545", "anime": {"name": "Gaba Kawa"}}, {"ratings": "0", "anime": {"name": "Haku\u014dki Sekkaroku"}}]}