{"name": "anime", "isRoot": "yes", "children": [{"isMedia": "yes", "name": "TV", "children": [{"isGenre": "yes", "name": "science fiction", "children": [{"isTheme": "yes", "name": "technology", "children": [{"isMovie": "yes", "name": "Galilei Donna"}, {"isMovie": "yes", "name": "Gad Guard"}, {"isMovie": "yes", "name": "MegaMan NT Warrior"}, {"isMovie": "yes", "name": "Accel World"}, {"isMovie": "yes", "name": "Denn\u014d Coil"}, {"isMovie": "yes", "name": "Space Brothers"}, {"isMovie": "yes", "name": "Solty Rei"}]}]}]}]}