{"name": "manga", "isRoot": "yes", "children": [{"isMedia": "yes", "name": "manga", "children": [{"isGenre": "yes", "name": "drama", "children": [{"isTheme": "yes", "name": "revenge", "children": [{"isMovie": "yes", "name": "Suikoden III"}, {"isMovie": "yes", "name": "Vinland Saga"}, {"isMovie": "yes", "name": "Book of Human Insects"}, {"isMovie": "yes", "name": "Kenji"}, {"isMovie": "yes", "name": "Kurosagi - The Black Swindler"}, {"isMovie": "yes", "name": "Skip Beat!"}, {"isMovie": "yes", "name": "Skyhigh"}, {"isMovie": "yes", "name": "Kamen no Romanesque"}, {"isMovie": "yes", "name": "Doubt"}, {"isMovie": "yes", "name": "Skyhigh: Shinsh\u014d"}, {"isMovie": "yes", "name": "Flowers of Evil"}, {"isMovie": "yes", "name": "\u00dcbel Blatt"}, {"isMovie": "yes", "name": "Skyhigh Karma"}, {"isMovie": "yes", "name": "Gankutsuou"}, {"isMovie": "yes", "name": "Berserk"}]}]}]}]}