{"ratings": [{"ratings": "8.3268", "anime": {"name": "Anthem of the Heart"}}, {"ratings": "7.9154", "anime": {"name": "Colorful"}}, {"ratings": "7.8243", "anime": {"name": "Prince of Light - The Legend of Ramayana"}}, {"ratings": "7.4681", "anime": {"name": "Tansuwarashi"}}, {"ratings": "7.3782", "anime": {"name": "Harmonie"}}, {"ratings": "7.3473", "anime": {"name": "Shakugan no Shana"}}, {"ratings": "7.2091", "anime": {"name": "Saiyuki: Requiem"}}, {"ratings": "7.2052", "anime": {"name": "Wasurenagumo"}}, {"ratings": "7.1706", "anime": {"name": "Konjiki no Gash Bell: 101 Banme no Mamono"}}, {"ratings": "7", "anime": {"name": "Gegege no Kitar\u014d: Saiky\u014d Y\u014dkai Gundan! Nihon J\u014driku!!"}}, {"ratings": "6.9494", "anime": {"name": "Ugokie Kori no Tatehiki"}}, {"ratings": "6.5589", "anime": {"name": "Konjiki no Gash Bell!!"}}, {"ratings": "6.5071", "anime": {"name": "Mah\u014d Sensei Negima! Anime Final"}}, {"ratings": "6.3898", "anime": {"name": "Bayonetta: Bloody Fate"}}, {"ratings": "6.1463", "anime": {"name": "Ghost Sweeper Mikami"}}, {"ratings": "5.5441", "anime": {"name": "Gegege no Kitar\u014d: Nippon Bakuretsu!!"}}, {"ratings": "3.7143", "anime": {"name": "Dark Cat"}}, {"ratings": "0", "anime": {"name": "Gegege no Kitarou"}}, {"ratings": "0", "anime": {"name": "Gegege no Kitar\u014d: Gekitotsu!! Ijigen Y\u014dkai no Daihanran"}}]}