{"name": "anime", "isRoot": "yes", "children": [{"isMedia": "yes", "name": "TV", "children": [{"isGenre": "yes", "name": "mystery", "children": [{"isTheme": "yes", "name": "fanservice", "children": [{"isMovie": "yes", "name": "Fruit of Grisaia"}, {"isMovie": "yes", "name": "K"}, {"isMovie": "yes", "name": "Mysterious Girlfriend X"}, {"isMovie": "yes", "name": "Bakemonogatari"}, {"isMovie": "yes", "name": "Dusk maiden of Amnesia"}, {"isMovie": "yes", "name": "NAKAIMO - My Little Sister Is Among Them!"}, {"isMovie": "yes", "name": "Btooom!"}]}]}]}]}