{"name": "anime", "isRoot": "yes", "children": [{"isMedia": "yes", "name": "movie", "children": [{"isGenre": "yes", "name": "thriller", "children": [{"isTheme": "yes", "name": "detective", "children": [{"isMovie": "yes", "name": "Case Closed: The Fourteenth Target"}, {"isMovie": "yes", "name": "Detective Conan: Dimensional Sniper"}, {"isMovie": "yes", "name": "Detective Conan: Quarter of Silence"}, {"isMovie": "yes", "name": "Detective Conan: The Lost Ship in The Sky"}, {"isMovie": "yes", "name": "Detective Conan: Sunflowers of Inferno"}, {"isMovie": "yes", "name": "Detective Conan: The Eleventh Striker"}]}, {"isTheme": "yes", "name": "social-networking", "children": [{"isMovie": "yes", "name": "Eden of the East: Paradise Lost"}]}, {"isTheme": "yes", "name": "vampires", "children": [{"isMovie": "yes", "name": "Blood: The Last Vampire"}]}, {"isTheme": "yes", "name": "terrorists", "children": [{"isMovie": "yes", "name": "Detective Conan: The Lost Ship in The Sky"}, {"isMovie": "yes", "name": "Siamese - First Mission"}]}, {"isTheme": "yes", "name": "police", "children": [{"isMovie": "yes", "name": "Batman: Gotham Knight"}, {"isMovie": "yes", "name": "Detective Conan: Quarter of Silence"}, {"isMovie": "yes", "name": "Detective Conan: Sunflowers of Inferno"}, {"isMovie": "yes", "name": "Detective Conan: Dimensional Sniper"}, {"isMovie": "yes", "name": "Detective Conan: The Eleventh Striker"}]}, {"isTheme": "yes", "name": "society", "children": [{"isMovie": "yes", "name": "Eden of the East: Paradise Lost"}]}, {"isTheme": "yes", "name": "girls with guns", "children": [{"isMovie": "yes", "name": "Siamese - First Mission"}]}, {"isTheme": "yes", "name": "politics", "children": [{"isMovie": "yes", "name": "Eden of the East: Paradise Lost"}]}, {"isTheme": "yes", "name": "technology", "children": [{"isMovie": "yes", "name": "Lupin III: Dead or Alive"}]}, {"isTheme": "yes", "name": "Monsters", "children": [{"isMovie": "yes", "name": "King of Thorn"}]}, {"isTheme": "yes", "name": "superhero", "children": [{"isMovie": "yes", "name": "Batman: Gotham Knight"}]}, {"isTheme": "yes", "name": "crime", "children": [{"isMovie": "yes", "name": "Case Closed: The Fourteenth Target"}, {"isMovie": "yes", "name": "Detective Conan: Dimensional Sniper"}, {"isMovie": "yes", "name": "Detective Conan: Quarter of Silence"}, {"isMovie": "yes", "name": "Batman: Gotham Knight"}, {"isMovie": "yes", "name": "Lupin III: Dead or Alive"}, {"isMovie": "yes", "name": "Detective Conan: The Lost Ship in The Sky"}, {"isMovie": "yes", "name": "Detective Conan: Sunflowers of Inferno"}, {"isMovie": "yes", "name": "Detective Conan: The Eleventh Striker"}]}, {"isTheme": "yes", "name": "amnesia", "children": [{"isMovie": "yes", "name": "Eden of the East: Paradise Lost"}]}, {"isTheme": "yes", "name": "monsters", "children": [{"isMovie": "yes", "name": "Blood: The Last Vampire"}]}, {"isTheme": "yes", "name": "Dreams", "children": [{"isMovie": "yes", "name": "King of Thorn"}]}, {"isTheme": "yes", "name": "superpowers", "children": [{"isMovie": "yes", "name": "Shingeki no Kyojin Zenpen: Guren no Yumiya"}, {"isMovie": "yes", "name": "Shingeki no Kyojin K\u014dhen: Jiy\u016b no Tsubasa"}]}, {"isTheme": "yes", "name": "survival game", "children": [{"isMovie": "yes", "name": "Death Billiards"}]}, {"isTheme": "yes", "name": "post-apocalyptic", "children": [{"isMovie": "yes", "name": "Shingeki no Kyojin Zenpen: Guren no Yumiya"}, {"isMovie": "yes", "name": "Shingeki no Kyojin K\u014dhen: Jiy\u016b no Tsubasa"}]}, {"isTheme": "yes", "name": "ninja", "children": [{"isMovie": "yes", "name": "Naruto Shipp\u016bden: Blood Prison"}]}, {"isTheme": "yes", "name": "tragedy", "children": [{"isMovie": "yes", "name": "Shingeki no Kyojin Zenpen: Guren no Yumiya"}, {"isMovie": "yes", "name": "Shingeki no Kyojin K\u014dhen: Jiy\u016b no Tsubasa"}]}, {"isTheme": "yes", "name": "dreams", "children": [{"isMovie": "yes", "name": "Paprika"}]}, {"isTheme": "yes", "name": "Tragedy", "children": [{"isMovie": "yes", "name": "King of Thorn"}]}, {"isTheme": "yes", "name": "military", "children": [{"isMovie": "yes", "name": "Shingeki no Kyojin Zenpen: Guren no Yumiya"}, {"isMovie": "yes", "name": "Shingeki no Kyojin K\u014dhen: Jiy\u016b no Tsubasa"}, {"isMovie": "yes", "name": "Lupin III: Dead or Alive"}]}]}]}]}