{"name": "anime", "isRoot": "yes", "children": [{"isMedia": "yes", "name": "TV", "children": [{"isGenre": "yes", "name": "romance", "children": [{"isTheme": "yes", "name": "space", "children": [{"isMovie": "yes", "name": "Star Blazers 2199"}, {"isMovie": "yes", "name": "Banner of the Stars"}, {"isMovie": "yes", "name": "Classroom Crisis"}, {"isMovie": "yes", "name": "Crest of the Stars"}, {"isMovie": "yes", "name": "Star Blazers"}, {"isMovie": "yes", "name": "Infinite Ryvius"}, {"isMovie": "yes", "name": "Aquarion Evol"}, {"isMovie": "yes", "name": "Tytania"}]}]}]}]}